src/__init__.py
src/app.py
src/config.py
src/version.py
src/analyzer/__init__.py
src/analyzer/main.py
src/services/__init__.py
src/services/github_service.py
src/services/repo_service.py
src/utils/__init__.py
src/utils/logging.py
test_impact_analyzer-0.2.0.dist-info/METADATA
test_impact_analyzer-0.2.0.dist-info/WHEEL
test_impact_analyzer-0.2.0.dist-info/entry_points.txt
test_impact_analyzer-0.2.0.dist-info/top_level.txt
test_impact_analyzer-0.2.0.dist-info/RECORD
