Metadata-Version: 2.4
Name: test-impact-analyzer
Version: 0.2.0
Summary: A smart GitHub webhook service that analyzes PRs to determine test impact
Home-page: https://github.com/uppadhyayraj/test-impact-analyzer
Author: Raj Uppadhyay
Author-email: Raj Uppadhyay <uppadhyayraj@gmail.com>
License-Expression: MIT
Project-URL: Homepage, https://github.com/uppadhyayraj/test-impact-analyzer
Project-URL: Repository, https://github.com/uppadhyayraj/test-impact-analyzer.git
Classifier: Development Status :: 3 - Alpha
Classifier: Intended Audience :: Developers
Classifier: Topic :: Software Development :: Testing
Classifier: Programming Language :: Python :: 3
Classifier: Programming Language :: Python :: 3.9
Classifier: Programming Language :: Python :: 3.10
Classifier: Programming Language :: Python :: 3.11
Classifier: Operating System :: OS Independent
Requires-Python: >=3.9
Requires-Dist: flask>=3.0.0
Requires-Dist: pydantic>=2.0.0
Requires-Dist: pydantic-settings>=2.0.0
Requires-Dist: requests>=2.31.0
Requires-Dist: python-dotenv>=1.0.0
Requires-Dist: gitpython>=3.1.0
Requires-Dist: pytest>=8.0.0
Requires-Dist: pytest-cov>=4.1.0
Requires-Dist: astroid>=3.0.0
Requires-Dist: asyncio>=3.4.3
Requires-Dist: aiohttp>=3.9.0
Requires-Dist: typing-extensions>=4.9.0
Requires-Dist: colorlog>=6.8.0
Requires-Dist: openai>=1.0.0
Requires-Dist: langchain>=0.1.0
Requires-Dist: langchain-ollama>=0.1.0
Requires-Dist: crewai>=0.1.0
Dynamic: author
Dynamic: home-page
Dynamic: requires-python
